confection/__init__.py
confection/py.typed
confection/util.py
confection/tests/__init__.py
confection/tests/conftest.py
confection/tests/test_config.py
confection/tests/test_frozen_structures.py
confection/tests/util.py
confection-0.1.4.dist-info/LICENSE
confection-0.1.4.dist-info/METADATA
confection-0.1.4.dist-info/WHEEL
confection-0.1.4.dist-info/top_level.txt
confection-0.1.4.dist-info/zip-safe
confection-0.1.4.dist-info/RECORD
